forecat/__init__.py
forecat/__version__.py
forecat/archs.py
forecat/transformer.py
forecat/unet.py
forecat/utils.py
forecat-0.0.3.dist-info/LICENSE
forecat-0.0.3.dist-info/METADATA
forecat-0.0.3.dist-info/WHEEL
forecat-0.0.3.dist-info/RECORD
