Metadata-Version: 2.1
Name: forecat
Version: 0.0.3
Summary: Keras based Forescast model builder
Home-page: https://github.com/alquimodelia/forecat
License: LICENSE
Keywords: python,machine learning,forecast,model builder
Author: João Santos
Author-email: jotaflame@gmail.com
Requires-Python: >=3.9,<4.0
Classifier: License :: Other/Proprietary License
Classifier: Programming Language :: Python :: 3
Classifier: Programming Language :: Python :: 3.9
Classifier: Programming Language :: Python :: 3.10
Classifier: Programming Language :: Python :: 3.11
Classifier: Programming Language :: Python :: 3.12
Provides-Extra: jax
Provides-Extra: tensorflow
Provides-Extra: torch
Requires-Dist: jax ; extra == "jax"
Requires-Dist: keras-core
Requires-Dist: numpy
Requires-Dist: pandas
Requires-Dist: pytorch ; extra == "torch"
Requires-Dist: tensorflow ; extra == "tensorflow"
Project-URL: Bug Tracker, https://github.com/alquimodelia/forecat/issues
Project-URL: Documentation, https://alquimodelia.github.io/forecat/
Project-URL: Repository, https://github.com/alquimodelia/forecat
Project-URL: Source Code, https://github.com/alquimodelia/forecat
